soko_api/__init__.py
soko_api/__version__.py
soko_api/client.py
soko_api/lib/__init__.py
soko_api/lib/client_options.py
soko_api/rest_client.py
soko_api/utils/__init__.py
soko_api/utils/files.py
soko_api/utils/template.py
soko_api/utils/video.py
soko_api-0.0.11.dist-info/METADATA
soko_api-0.0.11.dist-info/WHEEL
soko_api-0.0.11.dist-info/RECORD
