Metadata-Version: 2.1
Name: soko-api
Version: 0.0.11
Summary: 
Author: TomasRences
Author-email: rencestomas@gmail.com
Requires-Python: >=3.9,<4.0
Classifier: Programming Language :: Python :: 3
Classifier: Programming Language :: Python :: 3.9
Classifier: Programming Language :: Python :: 3.10
Classifier: Programming Language :: Python :: 3.11
Requires-Dist: httpx (>=0.25.2,<0.26.0)
Requires-Dist: postgrest (>=0.16.8,<0.17.0)
Requires-Dist: requests (>=2.31.0,<3.0.0)
